README.md
setup.py
PressurePyLite/__init__.py
PressurePyLite/ardu.py
PressurePyLite/main.py
PressurePyLite/readCsv.py
PressurePyLite/sender.py
PressurePyLite.egg-info/PKG-INFO
PressurePyLite.egg-info/SOURCES.txt
PressurePyLite.egg-info/dependency_links.txt
PressurePyLite.egg-info/entry_points.txt
PressurePyLite.egg-info/requires.txt
PressurePyLite.egg-info/top_level.txt