Metadata-Version: 2.1
Name: PressurePyLite
Version: 0.0.8
Summary: Controls Arduinos to put pressure in a box
Home-page: https://github.com/thiloschild/PressurePyLite
Author: Thilo Schild
Author-email: work@thilo-schild.de
License: MIT
Platform: UNKNOWN
Classifier: Programming Language :: Python :: 3
Classifier: License :: OSI Approved :: MIT License
Classifier: Operating System :: OS Independent
Requires-Python: >=3.6
